djangomailup/__init__.py
djangomailup/client.py
djangomailup/conf.py
djangomailup/models.py
djangomailup/oauth2.py
djangomailup/utils.py
djangomailup-0.2.0.dist-info/DESCRIPTION.rst
djangomailup-0.2.0.dist-info/METADATA
djangomailup-0.2.0.dist-info/RECORD
djangomailup-0.2.0.dist-info/WHEEL
djangomailup-0.2.0.dist-info/metadata.json
djangomailup-0.2.0.dist-info/top_level.txt
